google/cloud/apigee_registry/__init__.py
google/cloud/apigee_registry/gapic_version.py
google/cloud/apigee_registry/py.typed
google/cloud/apigee_registry_v1/__init__.py
google/cloud/apigee_registry_v1/gapic_metadata.json
google/cloud/apigee_registry_v1/gapic_version.py
google/cloud/apigee_registry_v1/py.typed
google/cloud/apigee_registry_v1/services/__init__.py
google/cloud/apigee_registry_v1/services/provisioning/__init__.py
google/cloud/apigee_registry_v1/services/provisioning/async_client.py
google/cloud/apigee_registry_v1/services/provisioning/client.py
google/cloud/apigee_registry_v1/services/provisioning/transports/__init__.py
google/cloud/apigee_registry_v1/services/provisioning/transports/base.py
google/cloud/apigee_registry_v1/services/provisioning/transports/grpc.py
google/cloud/apigee_registry_v1/services/provisioning/transports/grpc_asyncio.py
google/cloud/apigee_registry_v1/services/provisioning/transports/rest.py
google/cloud/apigee_registry_v1/services/provisioning/transports/rest_base.py
google/cloud/apigee_registry_v1/services/registry/__init__.py
google/cloud/apigee_registry_v1/services/registry/async_client.py
google/cloud/apigee_registry_v1/services/registry/client.py
google/cloud/apigee_registry_v1/services/registry/pagers.py
google/cloud/apigee_registry_v1/services/registry/transports/__init__.py
google/cloud/apigee_registry_v1/services/registry/transports/base.py
google/cloud/apigee_registry_v1/services/registry/transports/grpc.py
google/cloud/apigee_registry_v1/services/registry/transports/grpc_asyncio.py
google/cloud/apigee_registry_v1/services/registry/transports/rest.py
google/cloud/apigee_registry_v1/services/registry/transports/rest_base.py
google/cloud/apigee_registry_v1/types/__init__.py
google/cloud/apigee_registry_v1/types/provisioning_service.py
google/cloud/apigee_registry_v1/types/registry_models.py
google/cloud/apigee_registry_v1/types/registry_service.py
google_cloud_apigee_registry-0.8.0.dist-info/licenses/LICENSE
google_cloud_apigee_registry-0.8.0.dist-info/METADATA
google_cloud_apigee_registry-0.8.0.dist-info/WHEEL
google_cloud_apigee_registry-0.8.0.dist-info/top_level.txt
google_cloud_apigee_registry-0.8.0.dist-info/RECORD
